{"ongoing_trials": {}, "hyperparameters": {"space": [{"class_name": "Int", "config": {"name": "nb_filters", "default": null, "conditions": [], "min_value": 4, "max_value": 6, "step": 1, "sampling": null}}, {"class_name": "Int", "config": {"name": "dilations", "default": null, "conditions": [], "min_value": 2, "max_value": 6, "step": 1, "sampling": null}}, {"class_name": "Choice", "config": {"name": "dropout_rate", "default": 0.0, "conditions": [], "values": [0.0, 0.05], "ordered": true}}, {"class_name": "Float", "config": {"name": "learning_rate", "default": 1e-05, "conditions": [], "min_value": 1e-05, "max_value": 0.01, "step": null, "sampling": "log"}}], "values": {"nb_filters": 4, "dilations": 2, "dropout_rate": 0.0, "learning_rate": 1e-05}}, "seed": 626, "seed_state": 666, "tried_so_far": ["3154c2e32e57619748334e7e15cf6ca5", "650285ee505a8a197e7069695eb2e3bd", "ef4cfe386b15364718f27d61961d48af", "bf4d462557304b9549edf4850ccc951d", "d12f2bc57faff0dadfeb1d556ddc9c67", "427b271cf607670af121b16f687c962a", "b4ef74b823745bf2a2d68b3f55fd2a38", "0faeba871caa49bacd6cac1aa63dc382", "3d32a0c619a269d5fcf8586a44ebd7d8", "ea03b978aa7f511409d56a5f5ff1943b"]}